odoo/addons/fieldservice_availability/README.rst
odoo/addons/fieldservice_availability/__init__.py
odoo/addons/fieldservice_availability/__manifest__.py
odoo/addons/fieldservice_availability/i18n/ca.po
odoo/addons/fieldservice_availability/i18n/es.po
odoo/addons/fieldservice_availability/i18n/fieldservice_availability.pot
odoo/addons/fieldservice_availability/i18n/it.po
odoo/addons/fieldservice_availability/models/__init__.py
odoo/addons/fieldservice_availability/models/fsm_blackout_day.py
odoo/addons/fieldservice_availability/models/fsm_blackout_group.py
odoo/addons/fieldservice_availability/models/fsm_delivery_time_range.py
odoo/addons/fieldservice_availability/models/fsm_stress_day.py
odoo/addons/fieldservice_availability/readme/CONTRIBUTORS.md
odoo/addons/fieldservice_availability/readme/DESCRIPTION.md
odoo/addons/fieldservice_availability/readme/USAGE.md
odoo/addons/fieldservice_availability/security/ir.model.access.csv
odoo/addons/fieldservice_availability/static/description/icon.png
odoo/addons/fieldservice_availability/static/description/index.html
odoo/addons/fieldservice_availability/tests/__init__.py
odoo/addons/fieldservice_availability/tests/test_fsm_delivery_time_range.py
odoo/addons/fieldservice_availability/views/fsm_blackout_day_templates.xml
odoo/addons/fieldservice_availability/views/fsm_delivery_time_range_templates.xml
odoo/addons/fieldservice_availability/views/fsm_stress_day_templates.xml
odoo/addons/fieldservice_availability/views/menu.xml
odoo_addon_fieldservice_availability-18.0.1.0.0.2.dist-info/METADATA
odoo_addon_fieldservice_availability-18.0.1.0.0.2.dist-info/WHEEL
odoo_addon_fieldservice_availability-18.0.1.0.0.2.dist-info/top_level.txt
odoo_addon_fieldservice_availability-18.0.1.0.0.2.dist-info/RECORD
